{"version": 0.6, "generator": "Overpass API 0.7.62.5 1bd436f1", "osm3s": {"timestamp_osm_base": "2025-05-08T15:34:51Z", "copyright": "The data included in this document is from www.openstreetmap.org. The data is made available under ODbL."}, "elements": [{"type": "node", "id": 1698478721, "lat": 31.2238806, "lon": 29.9420097, "tags": {"highway": "traffic_signals", "traffic_signals": "signal"}}, {"type": "node", "id": 5375841071, "lat": 31.2238842, "lon": 29.9418886, "tags": {"highway": "traffic_signals", "traffic_signals": "signal"}}]}